{
  "mqtt":["garden","192.168.10.115",1883,"test","test"],
  "ow":{
    "28FFADCE601705A3":{"emit":"t_soil1","item":"h_relay6"},
    "286164123FF96F55":{"emit":"t_soil2"},
    "28FFEF6D60170335":{"emit":"t_soil3"}
  },
  "items":{
    "h_relay1":[6,39,1,1],
    "h_relay2":[6,38,1,1],
    "h_relay3":[6,37,1,1],
    "h_relay4":[6,36,1,1],
    "h_relay5":[6,35,1,1],
    "h_relay6":[5,34,27,1],
    "h_relay7":[6,33,1,1],
    "h_relay8":[6,32,1,1],
    "h_auto":[6,29,1,1]
  },
  "in":{
    "40":{"emit":"/myhome/s_out/g_in1","scmd":"CLOSED","rcmd":"OPEN"},
    "41":{"emit":"/myhome/s_out/g_in2","scmd":"CLOSED","rcmd":"OPEN"},
    "42":{"emit":"/myhome/s_out/g_in3","scmd":"CLOSED","rcmd":"OPEN"},
    "43":{"emit":"/myhome/s_out/g_in4","scmd":"CLOSED","rcmd":"OPEN"},
    "44":{"emit":"/myhome/s_out/g_in5","scmd":"CLOSED","rcmd":"OPEN"},
    "45":{"emit":"/myhome/s_out/g_in6","scmd":"CLOSED","rcmd":"OPEN"},
    "46":{"emit":"/myhome/s_out/g_in7","scmd":"CLOSED","rcmd":"OPEN"},
    "47":{"emit":"/myhome/s_out/g_in8","scmd":"CLOSED","rcmd":"OPEN"}
  }
}
